pymemoryapi.py
pymemoryapi-1.0.0.0.0.dist-info/WHEEL
pymemoryapi-1.0.0.0.0.dist-info/METADATA
pymemoryapi-1.0.0.0.0.dist-info/RECORD
